kibitzr_keyring.py
kibitzr_keyring-0.0.1.dist-info/DESCRIPTION.rst
kibitzr_keyring-0.0.1.dist-info/METADATA
kibitzr_keyring-0.0.1.dist-info/RECORD
kibitzr_keyring-0.0.1.dist-info/WHEEL
kibitzr_keyring-0.0.1.dist-info/entry_points.txt
kibitzr_keyring-0.0.1.dist-info/metadata.json
kibitzr_keyring-0.0.1.dist-info/top_level.txt
