Metadata-Version: 2.0
Name: kibitzr-keyring
Version: 0.0.1
Summary: Keyring support for Kibitzr
Home-page: https://github.com/kibitzr/kibitzr-keyring
Author: Peter Demin
Author-email: kibitzrrr@gmail.com
License: MIT license
Keywords: kibitzr
Platform: UNKNOWN
Classifier: Development Status :: 2 - Pre-Alpha
Classifier: Intended Audience :: Developers
Classifier: License :: OSI Approved :: MIT License
Classifier: Natural Language :: English
Classifier: Programming Language :: Python :: 2
Classifier: Programming Language :: Python :: 2.6
Classifier: Programming Language :: Python :: 2.7
Classifier: Programming Language :: Python :: 3
Classifier: Programming Language :: Python :: 3.3
Classifier: Programming Language :: Python :: 3.4
Classifier: Programming Language :: Python :: 3.5
Requires-Dist: keyring
